<annotation>
	<folder></folder>
	<filename>5a04255c406d39d6e0e9dc8d0a90c4ca_jpg.rf.088403167b5e57332a28f652ebe88fef.jpg</filename>
	<path>5a04255c406d39d6e0e9dc8d0a90c4ca_jpg.rf.088403167b5e57332a28f652ebe88fef.jpg</path>
	<source>
		<database>roboflow.com</database>
	</source>
	<size>
		<width>640</width>
		<height>640</height>
		<depth>3</depth>
	</size>
	<segmented>0</segmented>
	<object>
		<name>Graffiti</name>
		<pose>Unspecified</pose>
		<truncated>0</truncated>
		<difficult>0</difficult>
		<occluded>0</occluded>
		<bndbox>
			<xmin>438</xmin>
			<xmax>453</xmax>
			<ymin>200</ymin>
			<ymax>233</ymax>
		</bndbox>
	</object>
	<object>
		<name>Graffiti</name>
		<pose>Unspecified</pose>
		<truncated>0</truncated>
		<difficult>0</difficult>
		<occluded>0</occluded>
		<bndbox>
			<xmin>490</xmin>
			<xmax>537</xmax>
			<ymin>182</ymin>
			<ymax>237</ymax>
		</bndbox>
	</object>
	<object>
		<name>Graffiti</name>
		<pose>Unspecified</pose>
		<truncated>0</truncated>
		<difficult>0</difficult>
		<occluded>0</occluded>
		<bndbox>
			<xmin>536</xmin>
			<xmax>629</xmax>
			<ymin>162</ymin>
			<ymax>235</ymax>
		</bndbox>
	</object>
</annotation>
