<annotation>
	<folder></folder>
	<filename>6bbda5110dc083ca8b4bcb1adee4a536_jpg.rf.e19238908d58db09efe2de757ce87317.jpg</filename>
	<path>6bbda5110dc083ca8b4bcb1adee4a536_jpg.rf.e19238908d58db09efe2de757ce87317.jpg</path>
	<source>
		<database>roboflow.com</database>
	</source>
	<size>
		<width>640</width>
		<height>640</height>
		<depth>3</depth>
	</size>
	<segmented>0</segmented>
	<object>
		<name>Graffiti</name>
		<pose>Unspecified</pose>
		<truncated>0</truncated>
		<difficult>0</difficult>
		<occluded>0</occluded>
		<bndbox>
			<xmin>40</xmin>
			<xmax>159</xmax>
			<ymin>236</ymin>
			<ymax>388</ymax>
		</bndbox>
	</object>
	<object>
		<name>Graffiti</name>
		<pose>Unspecified</pose>
		<truncated>0</truncated>
		<difficult>0</difficult>
		<occluded>0</occluded>
		<bndbox>
			<xmin>257</xmin>
			<xmax>570</xmax>
			<ymin>200</ymin>
			<ymax>392</ymax>
		</bndbox>
	</object>
	<object>
		<name>Graffiti</name>
		<pose>Unspecified</pose>
		<truncated>0</truncated>
		<difficult>0</difficult>
		<occluded>0</occluded>
		<bndbox>
			<xmin>576</xmin>
			<xmax>638</xmax>
			<ymin>135</ymin>
			<ymax>274</ymax>
		</bndbox>
	</object>
</annotation>
