<annotation>
	<folder></folder>
	<filename>95d02b192e3b09e738bc48b2ea9fe4f3_jpg.rf.81d7e825ee5fa8d6a9b7c463fa8d52ea.jpg</filename>
	<path>95d02b192e3b09e738bc48b2ea9fe4f3_jpg.rf.81d7e825ee5fa8d6a9b7c463fa8d52ea.jpg</path>
	<source>
		<database>roboflow.com</database>
	</source>
	<size>
		<width>640</width>
		<height>640</height>
		<depth>3</depth>
	</size>
	<segmented>0</segmented>
	<object>
		<name>Graffiti</name>
		<pose>Unspecified</pose>
		<truncated>0</truncated>
		<difficult>0</difficult>
		<occluded>0</occluded>
		<bndbox>
			<xmin>142</xmin>
			<xmax>178</xmax>
			<ymin>240</ymin>
			<ymax>271</ymax>
		</bndbox>
	</object>
	<object>
		<name>Graffiti</name>
		<pose>Unspecified</pose>
		<truncated>0</truncated>
		<difficult>0</difficult>
		<occluded>0</occluded>
		<bndbox>
			<xmin>182</xmin>
			<xmax>192</xmax>
			<ymin>248</ymin>
			<ymax>265</ymax>
		</bndbox>
	</object>
</annotation>
